Metadata-Version: 1.1
Name: esper-wave
Version: 0.1.0
Summary: Tool for displaying ESPER waveforms and variables
Home-page: https://github.com/bryerton/esper-wave
Author: Bryerton Shaw
Author-email: bryerton@triumf.ca
License: MIT
Keywords: esper monitoring control experiments
Platform: UNKNOWN
Classifier: Development Status :: 5 - Production/Stable
Classifier: Intended Audience :: Science/Research
Classifier: Environment :: Console
Classifier: Topic :: System :: Networking
Classifier: License :: OSI Approved :: MIT License
Classifier: Programming Language :: Python :: 2
Classifier: Programming Language :: Python :: 2.7
Classifier: Programming Language :: Python :: 3
Classifier: Programming Language :: Python :: 3.3
Classifier: Programming Language :: Python :: 3.4
Classifier: Programming Language :: Python :: 3.5
